match_arrays.py
match_arrays-0.0.1.dist-info/LICENSE
match_arrays-0.0.1.dist-info/METADATA
match_arrays-0.0.1.dist-info/WHEEL
match_arrays-0.0.1.dist-info/top_level.txt
match_arrays-0.0.1.dist-info/RECORD
