Metadata-Version: 2.1
Name: match-arrays
Version: 0.0.1
Summary: Matching of Numpy arrays
Home-page: https://github.com/moi90/match_arrays
Author: Simon-Martin Schröder
Author-email: martin.schroeder@nerdluecht.de
License: UNKNOWN
Platform: UNKNOWN
Classifier: Programming Language :: Python :: 3
Classifier: License :: OSI Approved :: MIT License
Classifier: Operating System :: OS Independent
Requires-Dist: numpy
